MRdataset/__init__.py
MRdataset/__mrdataset__.py
MRdataset/_version.py
MRdataset/base.py
MRdataset/bids.py
MRdataset/cli.py
MRdataset/common.py
MRdataset/config.py
MRdataset/dicom.py
MRdataset/dicom_utils.py
MRdataset/utils.py
mrdataset-0.33.dist-info/METADATA
mrdataset-0.33.dist-info/WHEEL
mrdataset-0.33.dist-info/entry_points.txt
mrdataset-0.33.dist-info/licenses/AUTHORS.rst
mrdataset-0.33.dist-info/licenses/LICENSE
mrdataset-0.33.dist-info/RECORD
