Metadata-Version: 2.1
Name: MRdataset
Version: 0.33
Summary: MRdataset
Project-URL: Homepage, https://github.com/Open-Minds-Lab/MRdataset
Project-URL: Documentation, https://open-minds-lab.github.io/MRdataset/
Author-email: Harsh Sinha <sinha.harsh@pitt.edu>, Pradeep Raamana <raamana@gmail.com>
License: Apache Software License 2.0
License-File: AUTHORS.rst
License-File: LICENSE
Keywords: MRdataset
Classifier: Development Status :: 2 - Pre-Alpha
Classifier: Intended Audience :: Developers
Classifier: License :: OSI Approved :: Apache Software License
Classifier: Natural Language :: English
Classifier: Programming Language :: Python :: 3.8
Requires-Python: >=3.8
Requires-Dist: dicom2nifti>=2.4.2
Requires-Dist: nibabel
Requires-Dist: numpy
Requires-Dist: protocol
Requires-Dist: pybids
Requires-Dist: pydicom
